calicropyield/__init__.py
calicropyield/credentials.py
calicropyield/loader.py
calicropyield/utils.py
calicropyield-0.1.6.dist-info/LICENSE
calicropyield-0.1.6.dist-info/METADATA
calicropyield-0.1.6.dist-info/WHEEL
calicropyield-0.1.6.dist-info/top_level.txt
calicropyield-0.1.6.dist-info/RECORD
