Metadata-Version: 2.1
Name: calicropyield
Version: 0.1.6
Summary: A multi-modal data downloader and processing library for California crop yield benchmarking
Author: Hamid Kamangir
Author-email: Hamid Kamangir <hamid.kamangir@gmail.com>
License: BSD 3-Clause License
Project-URL: Homepage, https://github.com/plant-ai-biophysics-lab/calicropyield-dev
Project-URL: Repository, https://github.com/plant-ai-biophysics-lab/calicropyield-dev
Requires-Python: >=3.8
License-File: LICENSE
Requires-Dist: pandas
Requires-Dist: xarray
Requires-Dist: rasterio
Requires-Dist: geopandas
Requires-Dist: shapely
Requires-Dist: gdown
Requires-Dist: numpy
